{
  "elements": [
    {
      "label": "Daily Collaborative Summary (12-12-25)",
      "type": "Project",
      "Status": "Completed",
      "description": "Summary of all tasks and outputs generated on December 12, 2025",
      "tags": "Academic",
      "reference_link": "Local_Ref",
      "id": "Daily Collaborative Summary (12-12-25)"
    },
    {
      "label": "Source-Anchored Workflow Design",
      "type": "Task",
      "Status": "Completed",
      "description": "Designed a workflow where students upload specific sources to prevent AI hallucinations",
      "tags": "Academic",
      "reference_link": "Local_Ref",
      "id": "Source-Anchored Workflow Design"
    },
    {
      "label": "Anti-Hallucination Protocol",
      "type": "Task",
      "Status": "Completed",
      "description": "Developed a strategy to force AI to cite sources or admit ignorance",
      "tags": "Academic",
      "reference_link": "Local_Ref",
      "id": "Anti-Hallucination Protocol"
    },
    {
      "label": "Fact-Checking Reporter Script",
      "type": "Task",
      "Status": "Completed",
      "description": "Created a script for students to verify AI answers against source texts",
      "tags": "Academic",
      "reference_link": "Local_Ref",
      "id": "Fact-Checking Reporter Script"
    },
    {
      "label": "PKG Reporting Codebooks (V1-V9)",
      "type": "Task",
      "Status": "Completed",
      "description": "Generated multiple versions of the reporting codebook for Kumu data extraction",
      "tags": "Academic",
      "reference_link": "Local_Ref",
      "id": "PKG Reporting Codebooks (V1-V9)"
    },
    {
      "label": "Student Reflection Protocol",
      "type": "Task",
      "Status": "Completed",
      "description": "Designed scripts for students to generate their own learning data (Success/Friction)",
      "tags": "Academic",
      "reference_link": "Local_Ref",
      "id": "Student Reflection Protocol"
    },
    {
      "label": "R Script Development (V1-V5)",
      "type": "Task",
      "Status": "Completed",
      "description": "Wrote R scripts to process student JSON text files for Kumu import",
      "tags": "Academic",
      "reference_link": "Local_Ref",
      "id": "R Script Development (V1-V5)"
    },
    {
      "label": "Adaptive Learning Website Strategy",
      "type": "Task",
      "Status": "Completed",
      "description": "Designed a 'Knowledge Shop' website strategy based on the 'Wisdom/IQ' model",
      "tags": "Academic",
      "reference_link": "Local_Ref",
      "id": "Adaptive Learning Website Strategy"
    },
    {
      "label": "SiteWoW Prototype Generation",
      "type": "Task",
      "Status": "Completed",
      "description": "Generated HTML/Tailwind code for the website prototype (Flip Cards, Nature Theme)",
      "tags": "Academic",
      "reference_link": "Local_Ref",
      "id": "SiteWoW Prototype Generation"
    },
    {
      "label": "Mass Balance AI Assets",
      "type": "Task",
      "Status": "Completed",
      "description": "Generated 4 content variations (Visual, Analyst, Pragmatist, Theorist) for Mass Balance",
      "tags": "Academic",
      "reference_link": "Local_Ref",
      "id": "Mass Balance AI Assets"
    },
    {
      "label": "AI Tools Page Creation",
      "type": "Task",
      "Status": "Completed",
      "description": "Created the HTML for the 'AI Tools' page with copy-able scripts",
      "tags": "Academic",
      "reference_link": "Local_Ref",
      "id": "AI Tools Page Creation"
    },
    {
      "label": "GitHub Pages Deployment Guide",
      "type": "Task",
      "Status": "Completed",
      "description": "Provided a step-by-step guide for hosting the website on GitHub Pages",
      "tags": "Academic",
      "reference_link": "Local_Ref",
      "id": "GitHub Pages Deployment Guide"
    },
    {
      "label": "Bridge Link Implementation",
      "type": "Task",
      "Status": "Completed",
      "description": "Added direct 'Get Source' links to Google Drive within the website prototype",
      "tags": "Academic",
      "reference_link": "Local_Ref",
      "id": "Bridge Link Implementation"
    },
    {
      "label": "VS Code / GitHub Troubleshooting",
      "type": "Task",
      "Status": "Completed",
      "description": "Resolved issues with file naming (index.html) and git commit workflow",
      "tags": "Academic",
      "reference_link": "Local_Ref",
      "id": "VS Code / GitHub Troubleshooting"
    },
    {
      "label": "Universal PKG Reporting Codebook (V11.0)",
      "type": "Task",
      "Status": "Completed",
      "description": "Applied the V11.0 Miner prompt to summarize the day's work",
      "tags": "Academic",
      "reference_link": "Local_Ref",
      "id": "Universal PKG Reporting Codebook (V11.0)"
    },
    {
      "label": "Food & Process Engineering Technology textbook.pdf",
      "type": "Source",
      "Status": "Completed",
      "description": "Textbook used for FE course content",
      "tags": "Academic",
      "reference_link": "Local_Ref",
      "id": "Food & Process Engineering Technology textbook.pdf"
    },
    {
      "label": "Data_Driven_Storytelling.pdf",
      "type": "Source",
      "Status": "Completed",
      "description": "Source for storytelling concepts",
      "tags": "Academic",
      "reference_link": "Local_Ref",
      "id": "Data_Driven_Storytelling.pdf"
    },
    {
      "label": "microlearning_sys-review25.pdf",
      "type": "Source",
      "Status": "Completed",
      "description": "Source for microlearning concepts",
      "tags": "Academic",
      "reference_link": "Local_Ref",
      "id": "microlearning_sys-review25.pdf"
    },
    {
      "label": "R Paul Singh Food Engineering.pdf",
      "type": "Source",
      "Status": "Completed",
      "description": "Primary textbook for FE course structure",
      "tags": "Academic",
      "reference_link": "Local_Ref",
      "id": "R Paul Singh Food Engineering.pdf"
    },
    {
      "label": "Handbook_of_Game_Based_Learning.pdf",
      "type": "Source",
      "Status": "Completed",
      "description": "Source for GBL concepts",
      "tags": "Academic",
      "reference_link": "Local_Ref",
      "id": "Handbook_of_Game_Based_Learning.pdf"
    },
    {
      "label": "adaptive_leanring.txt",
      "type": "Source",
      "Status": "Completed",
      "description": "Source for adaptive learning strategy",
      "tags": "Academic",
      "reference_link": "Local_Ref",
      "id": "adaptive_leanring.txt"
    },
    {
      "label": "SiteWoW_reengineering-Next Steps.md",
      "type": "Source",
      "Status": "Completed",
      "description": "User notes on website vision",
      "tags": "Academic",
      "reference_link": "Local_Ref",
      "id": "SiteWoW_reengineering-Next Steps.md"
    }
  ],
  "connections": [
    {
      "from": "Daily Collaborative Summary (12-12-25)",
      "to": "Source-Anchored Workflow Design",
      "type": "+",
      "Description": "includes_task",
      "Spoke": "Academic"
    },
    {
      "from": "Daily Collaborative Summary (12-12-25)",
      "to": "Anti-Hallucination Protocol",
      "type": "+",
      "Description": "includes_task",
      "Spoke": "Academic"
    },
    {
      "from": "Daily Collaborative Summary (12-12-25)",
      "to": "Fact-Checking Reporter Script",
      "type": "+",
      "Description": "includes_task",
      "Spoke": "Academic"
    },
    {
      "from": "Daily Collaborative Summary (12-12-25)",
      "to": "PKG Reporting Codebooks (V1-V9)",
      "type": "+",
      "Description": "includes_task",
      "Spoke": "Academic"
    },
    {
      "from": "Daily Collaborative Summary (12-12-25)",
      "to": "Student Reflection Protocol",
      "type": "+",
      "Description": "includes_task",
      "Spoke": "Academic"
    },
    {
      "from": "Daily Collaborative Summary (12-12-25)",
      "to": "R Script Development (V1-V5)",
      "type": "+",
      "Description": "includes_task",
      "Spoke": "Academic"
    },
    {
      "from": "Daily Collaborative Summary (12-12-25)",
      "to": "Adaptive Learning Website Strategy",
      "type": "+",
      "Description": "includes_task",
      "Spoke": "Academic"
    },
    {
      "from": "Daily Collaborative Summary (12-12-25)",
      "to": "SiteWoW Prototype Generation",
      "type": "+",
      "Description": "includes_task",
      "Spoke": "Academic"
    },
    {
      "from": "Daily Collaborative Summary (12-12-25)",
      "to": "Mass Balance AI Assets",
      "type": "+",
      "Description": "includes_task",
      "Spoke": "Academic"
    },
    {
      "from": "Daily Collaborative Summary (12-12-25)",
      "to": "AI Tools Page Creation",
      "type": "+",
      "Description": "includes_task",
      "Spoke": "Academic"
    },
    {
      "from": "Daily Collaborative Summary (12-12-25)",
      "to": "GitHub Pages Deployment Guide",
      "type": "+",
      "Description": "includes_task",
      "Spoke": "Academic"
    },
    {
      "from": "Daily Collaborative Summary (12-12-25)",
      "to": "Bridge Link Implementation",
      "type": "+",
      "Description": "includes_task",
      "Spoke": "Academic"
    },
    {
      "from": "Daily Collaborative Summary (12-12-25)",
      "to": "VS Code / GitHub Troubleshooting",
      "type": "+",
      "Description": "includes_task",
      "Spoke": "Academic"
    },
    {
      "from": "Daily Collaborative Summary (12-12-25)",
      "to": "Universal PKG Reporting Codebook (V11.0)",
      "type": "+",
      "Description": "includes_task",
      "Spoke": "Academic"
    },
    {
      "from": "Source-Anchored Workflow Design",
      "to": "Anti-Hallucination Protocol",
      "type": ">",
      "Description": "requires",
      "Spoke": "Academic"
    },
    {
      "from": "Adaptive Learning Website Strategy",
      "to": "SiteWoW Prototype Generation",
      "type": ">",
      "Description": "leads_to",
      "Spoke": "Academic"
    },
    {
      "from": "SiteWoW Prototype Generation",
      "to": "Mass Balance AI Assets",
      "type": "+",
      "Description": "contains_content",
      "Spoke": "Academic"
    },
    {
      "from": "SiteWoW Prototype Generation",
      "to": "AI Tools Page Creation",
      "type": "+",
      "Description": "links_to",
      "Spoke": "Academic"
    },
    {
      "from": "GitHub Pages Deployment Guide",
      "to": "SiteWoW Prototype Generation",
      "type": ">",
      "Description": "deploys",
      "Spoke": "Academic"
    },
    {
      "from": "Bridge Link Implementation",
      "to": "Mass Balance AI Assets",
      "type": ">",
      "Description": "accesses",
      "Spoke": "Academic"
    },
    {
      "from": "VS Code / GitHub Troubleshooting",
      "to": "GitHub Pages Deployment Guide",
      "type": "!",
      "Description": "resolves_issue_in",
      "Spoke": "Academic"
    },
    {
      "from": "Source-Anchored Workflow Design",
      "to": "Food & Process Engineering Technology textbook.pdf",
      "type": "@",
      "Description": "uses_as_anchor",
      "Spoke": "Academic"
    },
    {
      "from": "Adaptive Learning Website Strategy",
      "to": "adaptive_leanring.txt",
      "type": "@",
      "Description": "based_on",
      "Spoke": "Academic"
    },
    {
      "from": "Adaptive Learning Website Strategy",
      "to": "SiteWoW_reengineering-Next Steps.md",
      "type": "@",
      "Description": "incorporates",
      "Spoke": "Academic"
    }
  ]
}
